quantfeed/__init__.py
quantfeed/__version__.py
quantfeed/api.py
quantfeed-0.0.4.dist-info/METADATA
quantfeed-0.0.4.dist-info/WHEEL
quantfeed-0.0.4.dist-info/top_level.txt
quantfeed-0.0.4.dist-info/RECORD
