Metadata-Version: 2.1
Name: quantfeed
Version: 0.0.4
Summary: QuantBox Future Data Api
Home-page: https://data.quantbox.cn
Author: hetao
Author-email: 22002499@qq.com
License: MIT
Keywords: quantbox futures tick bar datacenter
Platform: UNKNOWN
Classifier: Programming Language :: Python :: 3
Classifier: License :: OSI Approved :: MIT License
Classifier: Operating System :: OS Independent
Requires-Python: >=3.7
Requires-Dist: requests
Requires-Dist: pandas
